py_clickshot/__init__.py
py_clickshot/cli.py
py_clickshot/html_writer.py
py_clickshot/input_listener.py
py_clickshot/recorder.py
py_clickshot/screenshot.py
py_clickshot/backends/cursor_base.py
py_clickshot/backends/grim_backend.py
py_clickshot/backends/hyprctl_cursor.py
py_clickshot/backends/maim_backend.py
py_clickshot/backends/screenshot_base.py
py_clickshot/backends/scrot_backend.py
py_clickshot/backends/xdotool_cursor.py
py_clickshot-1.1.1.dist-info/entry_points.txt
py_clickshot-1.1.1.dist-info/licenses/LICENSE
py_clickshot-1.1.1.dist-info/WHEEL
py_clickshot-1.1.1.dist-info/METADATA
py_clickshot-1.1.1.dist-info/RECORD
