Metadata-Version: 2.4
Name: py-clickshot
Version: 1.1.1
Summary: Record your step with screenshot automatically, comes with click annotated on the image
Requires-Python: >=3.9
License-File: LICENSE
Requires-Dist: click>=8.1.8
Requires-Dist: evdev>=1.9.2
Requires-Dist: pillow>=10.0.0
